{
    "indices": [
        {
            "date": "2026-03-03",
            "上证指数": 4122.676,
            "深证成指": 14022.392,
            "创业板指": 3209.482
        },
        {
            "date": "2026-03-04",
            "上证指数": 4082.474,
            "深证成指": 13917.752,
            "创业板指": 3164.371
        },
        {
            "date": "2026-03-05",
            "上证指数": 4108.567,
            "深证成指": 14088.839,
            "创业板指": 3216.939
        },
        {
            "date": "2026-03-06",
            "上证指数": 4124.194,
            "深证成指": 14172.627,
            "创业板指": 3229.302
        },
        {
            "date": "2026-03-09",
            "上证指数": 4096.602,
            "深证成指": 14067.503,
            "创业板指": 3208.582
        }
    ],
    "industry_fund_flow": [
        {
            "名称": "航空机场",
            "今日主力净流入-净额": NaN,
            "今日主力净流入最大股": "-"
        },
        {
            "名称": "铁路公路",
            "今日主力净流入-净额": NaN,
            "今日主力净流入最大股": "-"
        },
        {
            "名称": "物流",
            "今日主力净流入-净额": NaN,
            "今日主力净流入最大股": "-"
        },
        {
            "名称": "水泥",
            "今日主力净流入-净额": NaN,
            "今日主力净流入最大股": "-"
        },
        {
            "名称": "公用事业",
            "今日主力净流入-净额": NaN,
            "今日主力净流入最大股": "-"
        }
    ],
    "concept_fund_flow": [
        {
            "名称": "工程建设",
            "今日主力净流入-净额": NaN,
            "今日主力净流入最大股": "-"
        },
        {
            "名称": "交运设备",
            "今日主力净流入-净额": NaN,
            "今日主力净流入最大股": "-"
        },
        {
            "名称": "互联网服务",
            "今日主力净流入-净额": NaN,
            "今日主力净流入最大股": "-"
        },
        {
            "名称": "造纸印刷",
            "今日主力净流入-净额": NaN,
            "今日主力净流入最大股": "-"
        },
        {
            "名称": "酿酒概念",
            "今日主力净流入-净额": NaN,
            "今日主力净流入最大股": "-"
        }
    ]
}