{
    "indices": [
        {
            "date": "2025-09-22",
            "上证指数": 3828.576,
            "深证成指": 13157.974,
            "创业板指": 3107.887
        },
        {
            "date": "2025-09-23",
            "上证指数": 3821.833,
            "深证成指": 13119.817,
            "创业板指": 3114.553
        },
        {
            "date": "2025-09-24",
            "上证指数": 3853.642,
            "深证成指": 13356.143,
            "创业板指": 3185.571
        },
        {
            "date": "2025-09-25",
            "上证指数": 3853.302,
            "深证成指": 13445.896,
            "创业板指": 3235.765
        },
        {
            "date": "2025-09-26",
            "上证指数": 3828.106,
            "深证成指": 13208.996,
            "创业板指": 3151.53
        }
    ],
    "industry_fund_flow": [
        {
            "名称": "航天航空",
            "今日主力净流入-净额": 836654528.0,
            "今日主力净流入最大股": "航发动力"
        },
        {
            "名称": "风电设备",
            "今日主力净流入-净额": 793117808.0,
            "今日主力净流入最大股": "明阳智能"
        },
        {
            "名称": "汽车整车",
            "今日主力净流入-净额": 719148032.0,
            "今日主力净流入最大股": "赛力斯"
        },
        {
            "名称": "化纤行业",
            "今日主力净流入-净额": 343059328.0,
            "今日主力净流入最大股": "皖维高新"
        },
        {
            "名称": "银行",
            "今日主力净流入-净额": 280451584.0,
            "今日主力净流入最大股": "农业银行"
        }
    ],
    "concept_fund_flow": [
        {
            "名称": "超级品牌",
            "今日主力净流入-净额": 966474752.0,
            "今日主力净流入最大股": "贵州茅台"
        },
        {
            "名称": "氟化工",
            "今日主力净流入-净额": 575271840.0,
            "今日主力净流入最大股": "天际股份"
        },
        {
            "名称": "磷化工",
            "今日主力净流入-净额": 535326512.0,
            "今日主力净流入最大股": "天际股份"
        },
        {
            "名称": "净水概念",
            "今日主力净流入-净额": 499184208.0,
            "今日主力净流入最大股": "美的集团"
        },
        {
            "名称": "煤化工",
            "今日主力净流入-净额": 438918384.0,
            "今日主力净流入最大股": "皖维高新"
        }
    ]
}