{
    "indices": [
        {
            "date": "2025-04-24",
            "上证指数": 3297.288,
            "深证成指": 9878.315,
            "创业板指": 1935.858
        },
        {
            "date": "2025-04-25",
            "上证指数": 3295.06,
            "深证成指": 9917.055,
            "创业板指": 1947.186
        },
        {
            "date": "2025-04-28",
            "上证指数": 3288.415,
            "深证成指": 9855.196,
            "创业板指": 1934.457
        },
        {
            "date": "2025-04-29",
            "上证指数": 3286.655,
            "深证成指": 9849.802,
            "创业板指": 1931.942
        },
        {
            "date": "2025-04-30",
            "上证指数": 3279.031,
            "深证成指": 9899.821,
            "创业板指": 1948.03
        }
    ],
    "industry_fund_flow": [
        {
            "名称": "汽车零部件",
            "今日主力净流入-净额": 1747464192.0,
            "今日主力净流入最大股": "南方精工"
        },
        {
            "名称": "通用设备",
            "今日主力净流入-净额": 1428741232.0,
            "今日主力净流入最大股": "祥鑫科技"
        },
        {
            "名称": "专用设备",
            "今日主力净流入-净额": 1144452512.0,
            "今日主力净流入最大股": "海南华铁"
        },
        {
            "名称": "消费电子",
            "今日主力净流入-净额": 1133994752.0,
            "今日主力净流入最大股": "瀛通通讯"
        },
        {
            "名称": "综合行业",
            "今日主力净流入-净额": 1065050192.0,
            "今日主力净流入最大股": "常山北明"
        }
    ],
    "concept_fund_flow": [
        {
            "名称": "人工智能",
            "今日主力净流入-净额": 5049600768.0,
            "今日主力净流入最大股": "常山北明"
        },
        {
            "名称": "机器人概念",
            "今日主力净流入-净额": 4822016000.0,
            "今日主力净流入最大股": "南方精工"
        },
        {
            "名称": "云计算",
            "今日主力净流入-净额": 3280501760.0,
            "今日主力净流入最大股": "常山北明"
        },
        {
            "名称": "预亏预减",
            "今日主力净流入-净额": 3084120832.0,
            "今日主力净流入最大股": "常山北明"
        },
        {
            "名称": "信创",
            "今日主力净流入-净额": 2832718848.0,
            "今日主力净流入最大股": "常山北明"
        }
    ]
}